biotranslator/__init__.py
biotranslator/biotranslator_function.py
biotranslator/biotranslator/__init__.py
biotranslator/biotranslator/_encoder.py
biotranslator/config/__init__.py
biotranslator/config/_config.py
biotranslator/loader/__init__.py
biotranslator/loader/_bioloader.py
biotranslator/metrics/__init__.py
biotranslator/metrics/_auroc.py
biotranslator/metrics/_micro_auroc.py
biotranslator/metrics/_roc.py
biotranslator/text_encoder/__init__.py
biotranslator/text_encoder/_datasets.py
biotranslator/text_encoder/_get_data.py
biotranslator/text_encoder/_nn.py
biotranslator/text_encoder/_train.py
biotranslator/trainer/__init__.py
biotranslator/trainer/_graph_trainer.py
biotranslator/trainer/_sequence_trainer.py
biotranslator/trainer/_trainer.py
biotranslator/trainer/_vector_trainer.py
biotranslator/utils/__init__.py
biotranslator/utils/_utils.py
biotranslator-0.1.1.dist-info/METADATA
biotranslator-0.1.1.dist-info/WHEEL
biotranslator-0.1.1.dist-info/top_level.txt
biotranslator-0.1.1.dist-info/RECORD
