Metadata-Version: 2.1
Name: biotranslator
Version: 0.1.1
Summary: BioTranslator: Cross-modal Translation for Zero-shot Biomedical Classification
Home-page: https://github.com/ywzhao2002/biotranslator
Author: Hanwen Xu, Yunwei Zhao, Addie Woicik, Hoifung Poon, Russ B.Altman, Sheng Wang
Author-email: swang91@uw.edu
Maintainer-email: Hanwen Xu <xuhw@cs.washington.edu>, Yunwei Zhao <yzhao4@cs.washington.edu>
License: MIT Licence
Project-URL: Documentation, https://biotranslator.readthedocs.io/en/latest/
Project-URL: Source, https://github.com/HanwenXuTHU/BioTranslatorProject
Keywords: pip,BioTranslator
Platform: any
Classifier: Intended Audience :: Developers
Classifier: Intended Audience :: Science/Research
Classifier: Natural Language :: English
Classifier: Operating System :: POSIX :: Linux
Classifier: Programming Language :: Python :: 3
Classifier: Programming Language :: Python :: 3.7
Classifier: Topic :: Scientific/Engineering :: Bio-Informatics
Requires-Dist: sentence-transformers
Requires-Dist: anndata (>=0.6.4)
Requires-Dist: fbpca (>=1.0)
Requires-Dist: umap-learn (>=0.3.10)
Requires-Dist: matplotlib (>=2.0.2)
Requires-Dist: numpy (>=1.16.4)
Requires-Dist: scipy (>=1.3.1)
Requires-Dist: scikit-learn (>=0.21.3)
Requires-Dist: scanorama (>=1.7.1)
Requires-Dist: torch (==1.7.1)
Requires-Dist: pandas
Requires-Dist: tqdm
Requires-Dist: networkx
Requires-Dist: gensim
Requires-Dist: nltk
Requires-Dist: torchvision (==0.8.2)
Provides-Extra: doc
Requires-Dist: myst-parser ; extra == 'doc'
